odoo8_addon_picking_dispatch-8.0.1.2.3.99.dev54-py3.8-nspkg.pth
odoo_addons/picking_dispatch/README.rst
odoo_addons/picking_dispatch/__init__.py
odoo_addons/picking_dispatch/__openerp__.py
odoo_addons/picking_dispatch/company.py
odoo_addons/picking_dispatch/cron_data.xml
odoo_addons/picking_dispatch/picking_dispatch.py
odoo_addons/picking_dispatch/picking_dispatch_report.xml
odoo_addons/picking_dispatch/picking_dispatch_sequence.xml
odoo_addons/picking_dispatch/picking_dispatch_view.xml
odoo_addons/picking_dispatch/picking_dispatch_workflow.xml
odoo_addons/picking_dispatch/product.py
odoo_addons/picking_dispatch/stock.py
odoo_addons/picking_dispatch/i18n/am.po
odoo_addons/picking_dispatch/i18n/ar.po
odoo_addons/picking_dispatch/i18n/bg.po
odoo_addons/picking_dispatch/i18n/bs.po
odoo_addons/picking_dispatch/i18n/ca.po
odoo_addons/picking_dispatch/i18n/ca_ES.po
odoo_addons/picking_dispatch/i18n/cs.po
odoo_addons/picking_dispatch/i18n/da.po
odoo_addons/picking_dispatch/i18n/de.po
odoo_addons/picking_dispatch/i18n/el_GR.po
odoo_addons/picking_dispatch/i18n/en_AU.po
odoo_addons/picking_dispatch/i18n/en_GB.po
odoo_addons/picking_dispatch/i18n/es.po
odoo_addons/picking_dispatch/i18n/es_AR.po
odoo_addons/picking_dispatch/i18n/es_BO.po
odoo_addons/picking_dispatch/i18n/es_CL.po
odoo_addons/picking_dispatch/i18n/es_CO.po
odoo_addons/picking_dispatch/i18n/es_CR.po
odoo_addons/picking_dispatch/i18n/es_DO.po
odoo_addons/picking_dispatch/i18n/es_EC.po
odoo_addons/picking_dispatch/i18n/es_ES.po
odoo_addons/picking_dispatch/i18n/es_MX.po
odoo_addons/picking_dispatch/i18n/es_PE.po
odoo_addons/picking_dispatch/i18n/es_PY.po
odoo_addons/picking_dispatch/i18n/es_VE.po
odoo_addons/picking_dispatch/i18n/et.po
odoo_addons/picking_dispatch/i18n/eu.po
odoo_addons/picking_dispatch/i18n/fa.po
odoo_addons/picking_dispatch/i18n/fi.po
odoo_addons/picking_dispatch/i18n/fr.po
odoo_addons/picking_dispatch/i18n/fr_CA.po
odoo_addons/picking_dispatch/i18n/fr_CH.po
odoo8_addon_picking_dispatch-8.0.1.2.3.99.dev54.dist-info/METADATA
odoo8_addon_picking_dispatch-8.0.1.2.3.99.dev54.dist-info/WHEEL
odoo8_addon_picking_dispatch-8.0.1.2.3.99.dev54.dist-info/namespace_packages.txt
odoo8_addon_picking_dispatch-8.0.1.2.3.99.dev54.dist-info/top_level.txt
odoo8_addon_picking_dispatch-8.0.1.2.3.99.dev54.dist-info/RECORD
